polen_donation_api/__init__.py
polen_donation_api-0.0.2.dist-info/LICENSE
polen_donation_api-0.0.2.dist-info/METADATA
polen_donation_api-0.0.2.dist-info/WHEEL
polen_donation_api-0.0.2.dist-info/top_level.txt
polen_donation_api-0.0.2.dist-info/RECORD
