Metadata-Version: 2.1
Name: polen-donation-api
Version: 0.0.2
Summary: A sua API de doações
Home-page: https://polen-donation.github.io/polen-docs/
Author: polen
Author-email: eupolinizo@opolen.com.br
License: UNKNOWN
Project-URL: Bug Tracker, https://github.com/Polen-Donation/polen-charity-donation-api/issues
Project-URL: Documentation, https://polen-donation.github.io/polen-docs/
Project-URL: Source, https://github.com/Polen-Donation/polen-charity-donation-api
Keywords: charity,OSC,ODS,Ongs,Ngos,Corporate,Donation,Doação,crowdfunding,Funding,Impact,Social,Giving
Platform: UNKNOWN
Classifier: Programming Language :: Python
Classifier: Programming Language :: Python :: 2.7
Classifier: Programming Language :: Python :: 3
Classifier: Programming Language :: Python :: 3.5
Classifier: Programming Language :: Python :: 3.6
Classifier: Programming Language :: Python :: 3.7
Classifier: Programming Language :: Python :: 3.8
Classifier: Programming Language :: Python :: 3.9
Classifier: License :: OSI Approved :: MIT License
Classifier: Operating System :: OS Independent
Requires-Python: >=2.7
Requires-Dist: requests
